tvdbapi_client/__init__.py
tvdbapi_client/api.py
tvdbapi_client/exceptions.py
tvdbapi_client/options.py
tvdbapi_client/timeutil.py
tvdbapi_client/tests/__init__.py
tvdbapi_client/tests/base.py
tvdbapi_client/tests/schema_helper.py
tvdbapi_client/tests/test_alt_api.py
tvdbapi_client/tests/test_api.py
tvdbapi_client/tests/test_options.py
tvdbapi_client/tests/test_timeutil.py
tvdbapi_client-0.1.5.data/data/etc/tvdbapi_client/gen.conf
tvdbapi_client-0.1.5.data/data/etc/tvdbapi_client/tvdbapi.conf.sample
tvdbapi_client-0.1.5.dist-info/DESCRIPTION.rst
tvdbapi_client-0.1.5.dist-info/METADATA
tvdbapi_client-0.1.5.dist-info/RECORD
tvdbapi_client-0.1.5.dist-info/WHEEL
tvdbapi_client-0.1.5.dist-info/entry_points.txt
tvdbapi_client-0.1.5.dist-info/metadata.json
tvdbapi_client-0.1.5.dist-info/pbr.json
tvdbapi_client-0.1.5.dist-info/top_level.txt
