Metadata-Version: 2.0
Name: tvdbapi-client
Version: 0.1.5
Summary: theTVDB API Client (json)
Home-page: https://github.com/shad7/tvdbapi_client
Author: shad7
Author-email: kenny.shad7@gmail.com
License: MIT
Keywords: tvdb,json,api,tv,espisode
Platform: UNKNOWN
Classifier: Development Status :: 4 - Beta
Classifier: Environment :: Console
Classifier: Environment :: Other Environment
Classifier: License :: OSI Approved :: MIT License
Classifier: Operating System :: OS Independent
Classifier: Programming Language :: Python
Classifier: Programming Language :: Python :: 2
Classifier: Programming Language :: Python :: 2.7
Classifier: Programming Language :: Python :: 3
Classifier: Programming Language :: Python :: 3.4
Classifier: Programming Language :: Python :: Implementation :: PyPy
Classifier: Topic :: Internet
Classifier: Topic :: Multimedia
Classifier: Topic :: Software Development :: Libraries :: Python Modules
Classifier: Topic :: Utilities
Requires-Dist: pbr (>=1.1.1)
Requires-Dist: twine
Requires-Dist: six (>=1.9.0)
Requires-Dist: oslo.config (>=1.9.0)
Requires-Dist: requests (>=2.7.0)
Requires-Dist: lockfile
Requires-Dist: CacheControl (>=0.11.5)
